README.md
setup.py
pyhocr/__init__.py
pyhocr/classes.py
pyhocr.egg-info/PKG-INFO
pyhocr.egg-info/SOURCES.txt
pyhocr.egg-info/dependency_links.txt
pyhocr.egg-info/requires.txt
pyhocr.egg-info/top_level.txt