Metadata-Version: 1.0
Name: pyhocr
Version: 4.0.0
Summary: Minimalistic library for parsing and navigating the hOCR
Home-page: https://github.com/algorythmik/python-hocr/
Author: Mojtaba
Author-email: smt.moji@gmail.com
License: UNKNOWN
Keywords: hocr parse
Platform: UNKNOWN
